[
  {
    "full_name": "fonnesbeck/statistical-analysis-python-tutorial",
    "stargazers_count": 1584,
    "open_issues_count": 1,
    "forks_count": 943
  },
  {
    "full_name": "swaroopch/byte-of-python",
    "stargazers_count": 2313,
    "open_issues_count": 11,
    "forks_count": 1079
  },
  {
    "full_name": "fonnesbeck/statistical-analysis-python-tutorial",
    "stargazers_count": 1584,
    "open_issues_count": 1,
    "forks_count": 943
  },
  {
    "full_name": "ptyadana/SQL-Data-Analysis-and-Visualization-Projects",
    "stargazers_count": 1282,
    "open_issues_count": 1,
    "forks_count": 516
  },
  {
    "full_name": "tailwindlabs/tailwindcss",
    "stargazers_count": 82760,
    "open_issues_count": 91,
    "forks_count": 4195
  }
]