[
  {
    "full_name": "fonnesbeck/statistical-analysis-python-tutorial",
    "stargazers_count": 1608,
    "open_issues_count": 1,
    "forks_count": 945
  },
  {
    "full_name": "swaroopch/byte-of-python",
    "stargazers_count": 2365,
    "open_issues_count": 11,
    "forks_count": 1080
  },
  {
    "full_name": "fonnesbeck/statistical-analysis-python-tutorial",
    "stargazers_count": 1608,
    "open_issues_count": 1,
    "forks_count": 945
  },
  {
    "full_name": "ptyadana/SQL-Data-Analysis-and-Visualization-Projects",
    "stargazers_count": 1430,
    "open_issues_count": 1,
    "forks_count": 553
  },
  {
    "full_name": "tailwindlabs/tailwindcss",
    "stargazers_count": 87780,
    "open_issues_count": 70,
    "forks_count": 4521
  }
]