[
  {
    "full_name": "fonnesbeck/statistical-analysis-python-tutorial",
    "stargazers_count": 1523,
    "open_issues_count": 1,
    "forks_count": 956
  },
  {
    "full_name": "swaroopch/byte-of-python",
    "stargazers_count": 2085,
    "open_issues_count": 10,
    "forks_count": 1063
  },
  {
    "full_name": "fonnesbeck/statistical-analysis-python-tutorial",
    "stargazers_count": 1523,
    "open_issues_count": 1,
    "forks_count": 956
  },
  {
    "full_name": "ptyadana/SQL-Data-Analysis-and-Visualization-Projects",
    "stargazers_count": 810,
    "open_issues_count": 1,
    "forks_count": 386
  },
  {
    "full_name": "tailwindlabs/tailwindcss",
    "stargazers_count": 70644,
    "open_issues_count": 20,
    "forks_count": 3644
  }
]