[
  {
    "full_name": "saucelabs/elemental-next",
    "stargazers_count": 13,
    "open_issues_count": 68,
    "forks_count": 3
  },
  {
    "full_name": "refinedev/hackathon-jan2023-guidelines",
    "stargazers_count": 10,
    "open_issues_count": 0,
    "forks_count": 1
  },
  {
    "full_name": "DataTalksClub/data-engineering-zoomcamp",
    "stargazers_count": 15360,
    "open_issues_count": 40,
    "forks_count": 3546
  },
  {
    "full_name": "justmarkham/scikit-learn-videos",
    "stargazers_count": 3597,
    "open_issues_count": 2,
    "forks_count": 2546
  },
  {
    "full_name": "rahuldkjain/github-profile-readme-generator",
    "stargazers_count": 17907,
    "open_issues_count": 318,
    "forks_count": 5262
  },
  {
    "full_name": "ptyadana/SQL-Data-Analysis-and-Visualization-Projects",
    "stargazers_count": 930,
    "open_issues_count": 1,
    "forks_count": 419
  },
  {
    "full_name": "fonnesbeck/statistical-analysis-python-tutorial",
    "stargazers_count": 1540,
    "open_issues_count": 1,
    "forks_count": 991
  },
  {
    "full_name": "swaroopch/byte-of-python",
    "stargazers_count": 2138,
    "open_issues_count": 11,
    "forks_count": 1115
  },
  {
    "full_name": "Akuli/python-tutorial",
    "stargazers_count": 1199,
    "open_issues_count": 7,
    "forks_count": 607
  },
  {
    "full_name": "mkumar7/Data-Analyst-Portfolio",
    "stargazers_count": 69,
    "open_issues_count": 0,
    "forks_count": 28
  },
  {
    "full_name": "nktnlx/data_analysis_portfolio",
    "stargazers_count": 116,
    "open_issues_count": 0,
    "forks_count": 28
  }
]