[
  {
    "full_name": "saucelabs/elemental-next",
    "stargazers_count": 21,
    "open_issues_count": 27,
    "forks_count": 11
  },
  {
    "full_name": "refinedev/hackathon-jan2023-guidelines",
    "stargazers_count": 8,
    "open_issues_count": 0,
    "forks_count": 0
  },
  {
    "full_name": "DataTalksClub/data-engineering-zoomcamp",
    "stargazers_count": 30197,
    "open_issues_count": 4,
    "forks_count": 6441
  },
  {
    "full_name": "justmarkham/scikit-learn-videos",
    "stargazers_count": 3698,
    "open_issues_count": 2,
    "forks_count": 2541
  },
  {
    "full_name": "rahuldkjain/github-profile-readme-generator",
    "stargazers_count": 22674,
    "open_issues_count": 375,
    "forks_count": 7510
  },
  {
    "full_name": "ptyadana/SQL-Data-Analysis-and-Visualization-Projects",
    "stargazers_count": 1424,
    "open_issues_count": 1,
    "forks_count": 553
  },
  {
    "full_name": "fonnesbeck/statistical-analysis-python-tutorial",
    "stargazers_count": 1606,
    "open_issues_count": 1,
    "forks_count": 945
  },
  {
    "full_name": "swaroopch/byte-of-python",
    "stargazers_count": 2357,
    "open_issues_count": 11,
    "forks_count": 1081
  },
  {
    "full_name": "Akuli/python-tutorial",
    "stargazers_count": 1440,
    "open_issues_count": 8,
    "forks_count": 619
  },
  {
    "full_name": "mkumar7/Data-Analyst-Portfolio",
    "stargazers_count": 118,
    "open_issues_count": 0,
    "forks_count": 33
  },
  {
    "full_name": "nktnlx/data_analysis_portfolio",
    "stargazers_count": 165,
    "open_issues_count": 0,
    "forks_count": 43
  }
]