[
  {
    "full_name": "saucelabs/elemental-next",
    "stargazers_count": 26,
    "open_issues_count": 43,
    "forks_count": 12
  },
  {
    "full_name": "refinedev/hackathon-jan2023-guidelines",
    "stargazers_count": 8,
    "open_issues_count": 0,
    "forks_count": 0
  },
  {
    "full_name": "DataTalksClub/data-engineering-zoomcamp",
    "stargazers_count": 33323,
    "open_issues_count": 7,
    "forks_count": 7081
  },
  {
    "full_name": "justmarkham/scikit-learn-videos",
    "stargazers_count": 3751,
    "open_issues_count": 0,
    "forks_count": 2546
  },
  {
    "full_name": "rahuldkjain/github-profile-readme-generator",
    "stargazers_count": 23696,
    "open_issues_count": 406,
    "forks_count": 8112
  },
  {
    "full_name": "ptyadana/SQL-Data-Analysis-and-Visualization-Projects",
    "stargazers_count": 1588,
    "open_issues_count": 1,
    "forks_count": 572
  },
  {
    "full_name": "fonnesbeck/statistical-analysis-python-tutorial",
    "stargazers_count": 1713,
    "open_issues_count": 1,
    "forks_count": 968
  },
  {
    "full_name": "swaroopch/byte-of-python",
    "stargazers_count": 2418,
    "open_issues_count": 11,
    "forks_count": 1090
  },
  {
    "full_name": "Akuli/python-tutorial",
    "stargazers_count": 1503,
    "open_issues_count": 8,
    "forks_count": 634
  },
  {
    "full_name": "mkumar7/Data-Analyst-Portfolio",
    "stargazers_count": 132,
    "open_issues_count": 0,
    "forks_count": 32
  },
  {
    "full_name": "nktnlx/data_analysis_portfolio",
    "stargazers_count": 171,
    "open_issues_count": 0,
    "forks_count": 44
  }
]